README.rst
setup.py
scripts/stormbot
stormbot/__init__.py
stormbot/bot.py
stormbot/storage.py
stormbot.egg-info/PKG-INFO
stormbot.egg-info/SOURCES.txt
stormbot.egg-info/dependency_links.txt
stormbot.egg-info/requires.txt
stormbot.egg-info/top_level.txt