Metadata-Version: 1.1
Name: stormbot
Version: 1.4.0
Summary: XMPP bot
Home-page: https://github.com/manoir/stormbot
Author: Paul Fariello
Author-email: paul@fariello.eu
License: UNKNOWN
Platform: UNKNOWN
Classifier: Environment :: Console
Classifier: Operating System :: POSIX
Classifier: Topic :: Communications :: Chat
Classifier: Programming Language :: Python
